{
  "type": "Feature",
  "properties": {
    "iso:country":"SG",
    "qs:gn_pop":0,
    "qs:name":"Johor Bahru",
    "qs:name_adm0":"Malaysia",
    "qs:name_adm1":"Johor",
    "qs:photos":4432,
    "qs:photos_1k":898,
    "qs:photos_9k":84,
    "qs:photos_9r":20,
    "qs:photos_all":18910,
    "qs:photos_sr":23,
    "qs:placetype":"County",
    "qs:pop_sr":"0",
    "qs:woe_adm0":23424901,
    "wof:name":"Johor Bahru",
    "wof:placetype":"county"
},
  "geometry": {"coordinates":[103.80432,1.345701],"type":"Point"}
}