{
  "type": "Feature",
  "properties": {
    "gn:admin1_code":"00",
    "gn:asciiname":"Kampong Bahru",
    "gn:cc2":"SG",
    "gn:country_code":"SG",
    "gn:dem":0,
    "gn:feature_class":"P",
    "gn:feature_code":"PPL",
    "gn:name":"Kampong Bahru",
    "gn:population":0,
    "gn:timezone":"Asia/Singapore",
    "iso:country":"SG",
    "name:und_x_variant":[
        "Kampong Baharu",
        "Kampong Bahru"
    ],
    "wof:name":"Kampong Bahru",
    "wof:placetype":"locality"
},
  "geometry": {"coordinates":[103.97028,1.41861],"type":"Point"}
}