{
  "type": "Feature",
  "properties": {
    "iso:country":"SG",
    "name:zho_x_preferred":[
        "\u4e2d\u5cc7\u9c81"
    ],
    "qs:gn_pop":0,
    "qs:name":"Tiong Bahru",
    "qs:name_adm0":"Singapore",
    "qs:name_adm1":"Central Singapore",
    "qs:photos":628,
    "qs:photos_1k":127,
    "qs:photos_9k":3,
    "qs:photos_9r":5,
    "qs:photos_all":628,
    "qs:photos_sr":8,
    "qs:placetype":"Town",
    "qs:pop_sr":"0",
    "qs:woe_adm0":23424948,
    "wd:wordcount":1258,
    "wof:name":"Tiong Bahru",
    "wof:placetype":"locality"
},
  "geometry": {"coordinates":[103.83199999999999,1.289479],"type":"Point"}
}