{
  "type": "Feature",
  "properties": {
    "gn:admin1_code":"03",
    "gn:asciiname":"Night Safari",
    "gn:country_code":"SG",
    "gn:dem":47,
    "gn:feature_class":"P",
    "gn:feature_code":"PPL",
    "gn:name":"Night Safari",
    "gn:population":0,
    "gn:timezone":"Asia/Singapore",
    "iso:country":"SG",
    "wof:name":"Night Safari",
    "wof:placetype":"locality"
},
  "geometry": {"coordinates":[103.78789,1.40226],"type":"Point"}
}