{
  "type": "Feature",
  "properties": {
    "gn:admin1_code":"00",
    "gn:asciiname":"Kampong Noordin",
    "gn:country_code":"SG",
    "gn:dem":0,
    "gn:feature_class":"P",
    "gn:feature_code":"PPL",
    "gn:name":"Kampong Noordin",
    "gn:population":0,
    "gn:timezone":"Asia/Singapore",
    "iso:country":"SG",
    "wof:name":"Kampong Noordin",
    "wof:placetype":"locality"
},
  "geometry": {"coordinates":[103.965,1.41778],"type":"Point"}
}