{
  "type": "Feature",
  "properties": {
    "iso:country":"SG",
    "name:msa_x_preferred":[
        "Seletar"
    ],
    "qs:gn_country":"SG",
    "qs:gn_fcode":"PPL",
    "qs:gn_pop":0,
    "qs:name":"Seletar",
    "qs:name_adm0":"Singapore",
    "qs:name_adm1":"Central Singapore",
    "qs:photos":2772,
    "qs:photos_1k":562,
    "qs:photos_9k":12,
    "qs:photos_9r":10,
    "qs:photos_all":2772,
    "qs:photos_sr":19,
    "qs:placetype":"Town",
    "qs:pop_sr":"0",
    "qs:woe_adm0":23424948,
    "wd:wordcount":423,
    "wof:name":"Seletar",
    "wof:placetype":"locality"
},
  "geometry": {"coordinates":[103.87417000000001,1.41],"type":"Point"}
}