{
  "type": "Feature",
  "properties": {
    "gn:admin1_code":"05",
    "gn:asciiname":"Sarang Rimau",
    "gn:country_code":"SG",
    "gn:dem":1,
    "gn:feature_class":"P",
    "gn:feature_code":"PPL",
    "gn:name":"Sarang Rimau",
    "gn:population":0,
    "gn:timezone":"Asia/Singapore",
    "iso:country":"SG",
    "wof:name":"Sarang Rimau",
    "wof:placetype":"locality"
},
  "geometry": {"coordinates":[103.80889000000001,1.25972],"type":"Point"}
}