{
  "type": "Feature",
  "properties": {
    "gn:country":"SG",
    "gn:fcode":"BLDG",
    "gn:pop":500,
    "iso:country":"SG",
    "qs:name":"Ministry of Information, Communications and the Arts",
    "qs:photos_9r":0,
    "qs:photos_sr":0,
    "qs:pop_sr":"2",
    "wof:name":"Ministry of Information, Communications and the Arts",
    "wof:placetype":"locality",
    "wof:population":500
},
  "geometry": {"coordinates":[103.84809,1.29063],"type":"Point"}
}