{
  "type": "Feature",
  "properties": {
    "gn:admin1_code":"00",
    "gn:asciiname":"Kampong Kebun Baharu",
    "gn:country_code":"SG",
    "gn:dem":15,
    "gn:feature_class":"P",
    "gn:feature_code":"PPL",
    "gn:name":"Kampong Kebun Baharu",
    "gn:population":0,
    "gn:timezone":"Asia/Singapore",
    "iso:country":"SG",
    "wof:name":"Kampong Kebun Baharu",
    "wof:placetype":"locality"
},
  "geometry": {"coordinates":[103.86667,1.36667],"type":"Point"}
}