{
  "type": "Feature",
  "properties": {
    "iso:country":"SG",
    "name:mar_x_preferred":[
        "\u0938\u0947\u0902\u091f\u094d\u0930\u0932 \u0915\u0945\u091a\u092e\u0947\u0902\u091f \u0928\u0945\u091a\u0930\u0932 \u0930\u093f\u091d\u0930\u094d\u0935\u094d\u0939"
    ],
    "name:msa_x_preferred":[
        "Hutan Simpanan Kawasan Tadahan Air Tengah"
    ],
    "name:nor_x_preferred":[
        "Central Water Catchment"
    ],
    "name:zho_x_preferred":[
        "\u4e2d\u592e\u96c6\u6c34\u533a\u81ea\u7136\u4fdd\u62a4\u533a"
    ],
    "qs:gn_pop":0,
    "qs:name":"Central Catchment Reserve",
    "qs:name_adm0":"Singapore",
    "qs:name_adm1":"Central Singapore",
    "qs:photos":4999,
    "qs:photos_1k":1000,
    "qs:photos_9k":22,
    "qs:photos_9r":14,
    "qs:photos_all":4999,
    "qs:photos_sr":24,
    "qs:placetype":"Town",
    "qs:pop_sr":"0",
    "qs:woe_adm0":23424948,
    "wd:wordcount":942,
    "wof:name":"Central Catchment Reserve",
    "wof:placetype":"locality"
},
  "geometry": {"coordinates":[103.82771,1.3562],"type":"Point"}
}