{
  "type": "Feature",
  "properties": {
    "iso:country":"SG",
    "name:ara_x_preferred":[
        "\u0643\u0627\u0644\u0627\u0646\u063a"
    ],
    "name:arz_x_preferred":[
        "\u0643\u0627\u0644\u0627\u0646\u062c"
    ],
    "name:deu_x_preferred":[
        "Kallang"
    ],
    "name:eng_x_preferred":[
        "Kallang"
    ],
    "name:fas_x_preferred":[
        "\u06a9\u0627\u0644\u0646\u06af"
    ],
    "name:fin_x_preferred":[
        "Kallang"
    ],
    "name:fra_x_preferred":[
        "Kallang"
    ],
    "name:ind_x_preferred":[
        "Kallang"
    ],
    "name:ita_x_preferred":[
        "Kallang"
    ],
    "name:jpn_x_preferred":[
        "\u52a0\u51b7"
    ],
    "name:msa_x_preferred":[
        "Kallang"
    ],
    "name:nld_x_preferred":[
        "Kallang"
    ],
    "name:por_x_preferred":[
        "Kallang"
    ],
    "name:rus_x_preferred":[
        "\u041a\u0430\u043b\u043b\u0430\u043d\u0433"
    ],
    "name:spa_x_preferred":[
        "Kallang"
    ],
    "name:vie_x_preferred":[
        "Kallang"
    ],
    "name:yue_x_preferred":[
        "\u52a0\u51b7"
    ],
    "name:zho_x_preferred":[
        "\u52a0\u51b7"
    ],
    "qs:gn_pop":0,
    "qs:name":"Kallang",
    "qs:name_adm0":"Singapore",
    "qs:name_adm1":"South East",
    "qs:photos":4998,
    "qs:photos_1k":1000,
    "qs:photos_9k":22,
    "qs:photos_9r":14,
    "qs:photos_all":4998,
    "qs:photos_sr":24,
    "qs:placetype":"Town",
    "qs:pop_sr":"0",
    "qs:woe_adm0":23424948,
    "wd:wordcount":2198,
    "wof:name":"Kallang",
    "wof:placetype":"locality"
},
  "geometry": {"coordinates":[103.87430500000001,1.300974],"type":"Point"}
}