{
  "type": "Feature",
  "properties": {
    "iso:country":"SG",
    "qs:gn_pop":0,
    "qs:name":"Kallang",
    "qs:name_adm0":"Singapore",
    "qs:name_adm1":"South East",
    "qs:photos":4998,
    "qs:photos_1k":1000,
    "qs:photos_9k":22,
    "qs:photos_9r":14,
    "qs:photos_all":4998,
    "qs:photos_sr":24,
    "qs:placetype":"Town",
    "qs:pop_sr":"0",
    "qs:woe_adm0":23424948,
    "wd:wordcount":2198,
    "wof:name":"Kallang",
    "wof:placetype":"locality"
},
  "geometry": {"coordinates":[103.87430500000001,1.300974],"type":"Point"}
}