{
  "type": "Feature",
  "properties": {
    "gn:admin1_code":"00",
    "gn:asciiname":"Sungai Mandai Village",
    "gn:cc2":"SG",
    "gn:country_code":"SG",
    "gn:dem":20,
    "gn:feature_class":"P",
    "gn:feature_code":"PPL",
    "gn:name":"Sungai Mandai Village",
    "gn:population":0,
    "gn:timezone":"Asia/Singapore",
    "iso:country":"SG",
    "name:und_x_variant":[
        "Sungai Mandai",
        "Sungai Mandai Village"
    ],
    "wof:name":"Sungai Mandai Village",
    "wof:placetype":"locality"
},
  "geometry": {"coordinates":[103.77694,1.41056],"type":"Point"}
}