{
  "type": "Feature",
  "properties": {
    "iso:country":"SG",
    "qs:gn_country":"SG",
    "qs:gn_fcode":"PPL",
    "qs:gn_pop":0,
    "qs:name":"Eunos",
    "qs:name_adm0":"Singapore",
    "qs:name_adm1":"North East",
    "qs:photos":5000,
    "qs:photos_1k":1000,
    "qs:photos_9k":22,
    "qs:photos_9r":14,
    "qs:photos_all":5000,
    "qs:photos_sr":24,
    "qs:placetype":"Town",
    "qs:pop_sr":"0",
    "qs:woe_adm0":23424948,
    "wd:wordcount":85,
    "wof:name":"Eunos",
    "wof:placetype":"locality"
},
  "geometry": {"coordinates":[103.89821999999999,1.32252],"type":"Point"}
}