{
  "type": "Feature",
  "properties": {
    "iso:country":"SG",
    "name:nor_x_preferred":[
        "Bishan"
    ],
    "qs:gn_pop":0,
    "qs:name":"Bishan",
    "qs:name_adm0":"Singapore",
    "qs:name_adm1":"Central Singapore",
    "qs:photos":4997,
    "qs:photos_1k":1000,
    "qs:photos_9k":22,
    "qs:photos_9r":14,
    "qs:photos_all":4997,
    "qs:photos_sr":24,
    "qs:placetype":"Town",
    "qs:pop_sr":"0",
    "qs:woe_adm0":23424948,
    "wd:wordcount":131,
    "wof:name":"Bishan",
    "wof:placetype":"locality"
},
  "geometry": {"coordinates":[103.83933,1.355343],"type":"Point"}
}