{
  "type": "Feature",
  "properties": {
    "iso:country":"SG",
    "name:deu_x_preferred":[
        "Jurong"
    ],
    "name:eng_x_preferred":[
        "Jurong East"
    ],
    "name:fas_x_preferred":[
        "\u062c\u0648\u0631\u0648\u0646\u06af \u0634\u0631\u0642\u06cc"
    ],
    "name:fin_x_preferred":[
        "Jurong East"
    ],
    "name:ind_x_preferred":[
        "Jurong East"
    ],
    "name:jpn_x_preferred":[
        "\u30b8\u30e5\u30ed\u30f3\u30fb\u30a4\u30fc\u30b9\u30c8"
    ],
    "name:mar_x_preferred":[
        "\u091c\u0941\u0930\u093e\u0901\u0917"
    ],
    "name:msa_x_preferred":[
        "Jurong East"
    ],
    "name:nld_x_preferred":[
        "Jurong East"
    ],
    "name:por_x_preferred":[
        "Jurong"
    ],
    "name:tgl_x_preferred":[
        "Jurong"
    ],
    "name:urd_x_preferred":[
        "\u062c\u0648\u0631\u0648\u0646\u06af \u0645\u0634\u0631\u0642\u06cc"
    ],
    "name:vie_x_preferred":[
        "\u0110\u00f4ng Jurong"
    ],
    "name:zho_x_preferred":[
        "\u88d5\u5eca\u6771"
    ],
    "qs:gn_pop":0,
    "qs:name":"Jurong East New Town",
    "qs:name_adm0":"Singapore",
    "qs:name_adm1":"South West",
    "qs:photos":2568,
    "qs:photos_1k":520,
    "qs:photos_9k":11,
    "qs:photos_9r":10,
    "qs:photos_all":2568,
    "qs:photos_sr":18,
    "qs:placetype":"Town",
    "qs:pop_sr":"0",
    "qs:woe_adm0":23424948,
    "wof:name":"Jurong East New Town",
    "wof:placetype":"locality"
},
  "geometry": {"coordinates":[103.738317,1.332867],"type":"Point"}
}